MANIFEST.in
README.rst
setup.py
docs/CHANGELOG.rst
docs/LICENSE.rst
slc/__init__.py
slc.permissiondump.egg-info/PKG-INFO
slc.permissiondump.egg-info/SOURCES.txt
slc.permissiondump.egg-info/dependency_links.txt
slc.permissiondump.egg-info/entry_points.txt
slc.permissiondump.egg-info/not-zip-safe
slc.permissiondump.egg-info/requires.txt
slc.permissiondump.egg-info/top_level.txt
slc/permissiondump/__init__.py
slc/permissiondump/dump_roles.py
slc/permissiondump/html_export.py
slc/permissiondump/static/jquery-ui.custom.js
slc/permissiondump/static/jquery.dynatree.min.js
slc/permissiondump/static/jquery.js
slc/permissiondump/static/ui.dynatree.css