Metadata-Version: 1.1
Name: slc.permissiondump
Version: 0.2.1
Summary: Visualize a tree of local roles assigned on Plone items.
Home-page: http://pypi.python.org/pypi/slc.permissiondump
Author: NiteoWeb Ltd.
Author-email: info@niteoweb.com
License: BSD
Platform: UNKNOWN
Classifier: Programming Language :: Python
Classifier: Framework :: Plone
